ppar/__init__.py
ppar/analytics.py
ppar/attribution.py
ppar/classification.py
ppar/columns.py
ppar/demo_data_sources.py
ppar/errors.py
ppar/format_chart.py
ppar/format_table.py
ppar/frequency.py
ppar/mapping.py
ppar/performance.py
ppar/py.typed
ppar/riskstatistics.py
ppar/utilities.py
ppar/demo_data/classifications/Economic Sector.csv
ppar/demo_data/classifications/Security.csv
ppar/demo_data/mappings/Security--to--Economic Sector.csv
ppar/demo_data/performance/Large-Cap Alpha Portfolio.csv
ppar/demo_data/performance/Large-Cap Benchmark.csv
ppar-0.1.2.dist-info/licenses/LICENSE
ppar-0.1.2.dist-info/METADATA
ppar-0.1.2.dist-info/WHEEL
ppar-0.1.2.dist-info/top_level.txt
ppar-0.1.2.dist-info/RECORD
