Metadata-Version: 2.4
Name: ppar
Version: 0.1.2
Summary: A python-based application that produces multi-period attribution, contribution, and benchmark-relative ex-post risk statistics.
Author-email: John Reynolds <jjjkreynolds@gmail.com>
License: Copyright (c) 2025, John D. Reynolds
Project-URL: Repository, https://github.com/JohnDReynolds/portfolio-performance-analytics
Keywords: portfolio,performance,analytics,attribution,brinson,fachler,risk,statistics
Requires-Python: >=3.12.1
License-File: LICENSE
Requires-Dist: great_tables>=0.17.0
Requires-Dist: lxml>=5.1.0
Requires-Dist: matplotlib>=3.8.2
Requires-Dist: numpy>=1.26.4
Requires-Dist: pandas>=2.2.2
Requires-Dist: polars>=1.16.0
Requires-Dist: pyarrow>=15.0.1
Requires-Dist: scipy>=1.12.0
Requires-Dist: seaborn>=0.13.2
Dynamic: license-file
